funpayparsers/__init__.py
funpayparsers/exceptions.py
funpayparsers/message_type_re.py
funpayparsers/py.typed
funpayparsers/parsers/__init__.py
funpayparsers/parsers/achievement_parser.py
funpayparsers/parsers/appdata_parser.py
funpayparsers/parsers/badge_parser.py
funpayparsers/parsers/base.py
funpayparsers/parsers/categories_parser.py
funpayparsers/parsers/chat_parser.py
funpayparsers/parsers/chat_previews_parser.py
funpayparsers/parsers/cpu_parser.py
funpayparsers/parsers/message_meta_parser.py
funpayparsers/parsers/messages_parser.py
funpayparsers/parsers/money_value_parser.py
funpayparsers/parsers/offer_fields_parser.py
funpayparsers/parsers/offer_previews_parser.py
funpayparsers/parsers/order_previews_parser.py
funpayparsers/parsers/page_header_parser.py
funpayparsers/parsers/private_chat_info_parser.py
funpayparsers/parsers/rating_parser.py
funpayparsers/parsers/reviews_parser.py
funpayparsers/parsers/transaction_previews_parser.py
funpayparsers/parsers/updates_parser.py
funpayparsers/parsers/user_preview_parser.py
funpayparsers/parsers/utils.py
funpayparsers/parsers/page_parsers/__init__.py
funpayparsers/parsers/page_parsers/chat_page_parser.py
funpayparsers/parsers/page_parsers/main_page_parser.py
funpayparsers/parsers/page_parsers/my_chips_page_parser.py
funpayparsers/parsers/page_parsers/my_offers_page_parser.py
funpayparsers/parsers/page_parsers/offer_page_parser.py
funpayparsers/parsers/page_parsers/order_page_parser.py
funpayparsers/parsers/page_parsers/profile_page_parser.py
funpayparsers/parsers/page_parsers/settings_page_parser.py
funpayparsers/parsers/page_parsers/subcategory_page_parser.py
funpayparsers/parsers/page_parsers/transactions_page_parser.py
funpayparsers/types/__init__.py
funpayparsers/types/base.py
funpayparsers/types/categories.py
funpayparsers/types/chat.py
funpayparsers/types/common.py
funpayparsers/types/common_page_elements.py
funpayparsers/types/enums.py
funpayparsers/types/finances.py
funpayparsers/types/messages.py
funpayparsers-0.5.10.dist-info/METADATA
funpayparsers-0.5.10.dist-info/WHEEL
funpayparsers-0.5.10.dist-info/RECORD
