Metadata-Version: 2.4
Name: funpayparsers
Version: 0.5.10
Summary: Set of parsers for FunPay website.
Project-URL: Telegram Channel, https://t.me/funpay_hub
Project-URL: Repository, https://github.com/funpayhub/funpayparsers
Project-URL: Issues, https://github.com/funpyahub/funpayparsers/issues
Author-email: Qvvonk <qvvonk@gmail.com>
Maintainer-email: Qvvonk <qvvonk@gmail.com>
License-Expression: MIT
Keywords: api,bot,funpay,funpayapi,funpaybot,funpayparser,parser
Classifier: Development Status :: 4 - Beta
Classifier: Programming Language :: Python :: 3.10
Classifier: Programming Language :: Python :: 3.11
Classifier: Programming Language :: Python :: 3.12
Classifier: Programming Language :: Python :: 3.13
Requires-Python: >=3.10
Requires-Dist: selectolax~=0.3.31
Requires-Dist: typing-extensions~=4.14.0
Requires-Dist: tzdata; platform_system == 'Windows'
Provides-Extra: dev
Requires-Dist: mypy>=1.17.0; extra == 'dev'
Requires-Dist: ruff; extra == 'dev'
Provides-Extra: tests
Requires-Dist: pytest; extra == 'tests'
